odoo/addons/partner_contact_company_propagation/README.rst
odoo/addons/partner_contact_company_propagation/__init__.py
odoo/addons/partner_contact_company_propagation/__manifest__.py
odoo/addons/partner_contact_company_propagation/i18n/es.po
odoo/addons/partner_contact_company_propagation/i18n/it.po
odoo/addons/partner_contact_company_propagation/i18n/partner_contact_company_propagation.pot
odoo/addons/partner_contact_company_propagation/models/__init__.py
odoo/addons/partner_contact_company_propagation/models/res_partner.py
odoo/addons/partner_contact_company_propagation/readme/CONTRIBUTORS.rst
odoo/addons/partner_contact_company_propagation/readme/DESCRIPTION.rst
odoo/addons/partner_contact_company_propagation/static/description/icon.png
odoo/addons/partner_contact_company_propagation/static/description/index.html
odoo/addons/partner_contact_company_propagation/tests/__init__.py
odoo/addons/partner_contact_company_propagation/tests/test_partner_contact_company_propagation.py
odoo14_addon_partner_contact_company_propagation-14.0.1.0.1.dev8.dist-info/METADATA
odoo14_addon_partner_contact_company_propagation-14.0.1.0.1.dev8.dist-info/WHEEL
odoo14_addon_partner_contact_company_propagation-14.0.1.0.1.dev8.dist-info/top_level.txt
odoo14_addon_partner_contact_company_propagation-14.0.1.0.1.dev8.dist-info/RECORD
